{
	"elements": [
		{
			"weight": 1.0,
			"key": "megacells:16m_crafting_storage",
			"data": {
				"float": true,
				"laggy": true,
				"top": true,
				"full": true
			}
		},
		{
			"weight": 1.0,
			"key": "megacells:1m_crafting_storage",
			"data": {
				"float": true,
				"laggy": true,
				"top": true,
				"full": true
			}
		},
		{
			"weight": 1.0,
			"key": "megacells:256m_crafting_storage",
			"data": {
				"float": true,
				"laggy": true,
				"top": true,
				"full": true
			}
		},
		{
			"weight": 1.0,
			"key": "megacells:4m_crafting_storage",
			"data": {
				"float": true,
				"laggy": true,
				"top": true,
				"full": true
			}
		},
		{
			"weight": 1.0,
			"key": "megacells:64m_crafting_storage",
			"data": {
				"float": true,
				"laggy": true,
				"top": true,
				"full": true
			}
		},
		{
			"weight": 1.0,
			"key": "megacells:mega_crafting_accelerator",
			"data": {
				"float": true,
				"laggy": true,
				"top": true,
				"full": true
			}
		},
		{
			"weight": 1.0,
			"key": "megacells:mega_crafting_monitor",
			"data": {
				"float": true,
				"laggy": true,
				"top": true,
				"full": true
			}
		},
		{
			"weight": 1.0,
			"key": "megacells:mega_crafting_unit",
			"data": {
				"float": true,
				"laggy": true,
				"top": true,
				"full": true
			}
		},
		{
			"weight": 1.0,
			"key": "megacells:mega_emc_interface",
			"data": {
				"float": true,
				"laggy": true,
				"top": true,
				"full": true
			}
		},
		{
			"weight": 1.0,
			"key": "megacells:mega_energy_cell",
			"data": {
				"float": true,
				"laggy": true,
				"top": true,
				"full": true
			}
		},
		{
			"weight": 1.0,
			"key": "megacells:mega_interface",
			"data": {
				"float": true,
				"laggy": true,
				"top": true,
				"full": true
			}
		},
		{
			"weight": 1.0,
			"key": "megacells:mega_pattern_provider",
			"data": {
				"float": true,
				"laggy": true,
				"top": true,
				"full": true
			}
		},
		{
			"weight": 1.0,
			"key": "megacells:sky_steel_block",
			"data": {
				"float": true,
				"laggy": false,
				"top": true,
				"full": true
			}
		}
	]
}
